clopy/__init__.py
clopy/clopy.py
clopy/tmpl.py
clopy-0.1.12.data/data/share/doc/glances/LICENSE
clopy-0.1.12.data/data/share/doc/glances/README.md
clopy-0.1.12.data/data/share/man/man1/clopy.1
clopy-0.1.12.dist-info/LICENSE
clopy-0.1.12.dist-info/METADATA
clopy-0.1.12.dist-info/WHEEL
clopy-0.1.12.dist-info/entry_points.txt
clopy-0.1.12.dist-info/top_level.txt
clopy-0.1.12.dist-info/RECORD
