Metadata-Version: 2.1
Name: clopy
Version: 0.1.12
Summary: General purpose templating program to quickly setup projects and files
Home-page: https://github.com/jmdaemon/bang
Author: Joseph Diza
Author-email: josephm.diza@gmail.com
License: MIT
Project-URL: Bug Tracker, https://github.com/jmdaemon/bang/issues
Platform: UNKNOWN
Requires-Python: >=3.6
License-File: LICENSE
Requires-Dist: argparse
Requires-Dist: jinja2
Requires-Dist: wora
